{"textures":{"0":"modelengine:entity/yeti"},"elements":[{"from":[5.428571,5.817931,6.7357984],"to":[10.571428,12.103645,11.307227],"rotation":{"angle":22.5,"axis":"x","origin":[8.0,12.315722,0.3444934]},"faces":{"east":{"uv":[10.875,0.0,11.875,1.375],"rotation":0,"texture":"#0","tintindex":0},"south":{"uv":[2.375,10.125,1.25,11.5],"rotation":0,"texture":"#0","tintindex":0},"north":{"uv":[1.125,10.125,0.0,11.5],"rotation":0,"texture":"#0","tintindex":0},"west":{"uv":[11.875,0.0,10.875,1.375],"rotation":0,"texture":"#0","tintindex":0},"up":{"uv":[11.625,13.0,12.75,12.0],"rotation":0,"texture":"#0","tintindex":0},"down":{"uv":[12.25,5.875,13.375,6.875],"rotation":0,"texture":"#0","tintindex":0}}}],"display":{"head":{"translation":[0.0,-6.4,0.0],"scale":[4.0,4.0,4.0]}}}