{"textures":{"0":"modelengine:entity/rabbit_tooth"},"elements":[{"from":[1.52,3.5252972,8.41],"to":[14.48,10.725298,8.41],"faces":{"south":{"uv":[4.5,10.0,0.0,12.5],"tintindex":0,"rotation":0,"texture":"#0"},"north":{"uv":[0.0,10.0,4.5,12.5],"tintindex":0,"rotation":0,"texture":"#0"}},"rotation":{"origin":[8.0,8.379999,8.41],"angle":45.0,"axis":"x"}},{"from":[1.52,2.0672073,4.9772077],"to":[14.48,4.9472065,4.9772077],"faces":{"south":{"uv":[9.5,0.0,5.0,1.0],"tintindex":0,"rotation":0,"texture":"#0"},"north":{"uv":[5.0,0.0,9.5,1.0],"tintindex":0,"rotation":0,"texture":"#0"}}}]}