{"textures":{"0":"modelengine:entity/fc_mechrider"},"elements":[{"from":[0.5,3.9,-9.700001],"to":[15.5,8.9,14.299999],"faces":{"east":{"uv":[5.75,8.125,6.375,11.125],"tintindex":0,"rotation":90,"texture":"#0"},"south":{"uv":[8.125,8.75,10.0,9.375],"tintindex":0,"rotation":0,"texture":"#0"},"north":{"uv":[8.125,8.75,10.0,9.375],"tintindex":0,"rotation":0,"texture":"#0"},"west":{"uv":[5.75,8.125,6.375,11.125],"tintindex":0,"rotation":90,"texture":"#0"},"up":{"uv":[8.125,6.375,10.0,9.375],"tintindex":0,"rotation":0,"texture":"#0"},"down":{"uv":[8.125,6.375,10.0,9.375],"tintindex":0,"rotation":0,"texture":"#0"}}}]}