{"textures":{"0":"modelengine:entity/easter_chick"},"elements":[{"from":[8.312322,3.464028,6.0],"to":[9.312322,8.464028,10.0],"faces":{"east":{"uv":[8.5,1.75,7.5,3.0],"tintindex":0,"rotation":0,"texture":"#0"},"south":{"uv":[8.75,6.25,8.5,7.5],"tintindex":0,"rotation":0,"texture":"#0"},"north":{"uv":[8.75,4.75,8.5,6.0],"tintindex":0,"rotation":0,"texture":"#0"},"west":{"uv":[2.75,7.5,1.75,8.75],"tintindex":0,"rotation":0,"texture":"#0"},"up":{"uv":[3.25,10.0,3.5,9.0],"tintindex":0,"rotation":0,"texture":"#0"},"down":{"uv":[3.75,9.0,4.0,10.0],"tintindex":0,"rotation":0,"texture":"#0"}},"rotation":{"origin":[8.812322,5.964028,8.0],"angle":22.5,"axis":"z"}}]}