{"textures":{"0":"modelengine:entity/christmas_pack"},"elements":[{"from":[6.0,17.0,0.0],"to":[18.0,19.0,2.0],"faces":{"east":{"uv":[1.8125,12.625,1.5625,12.875],"tintindex":0,"rotation":0,"texture":"#0"},"south":{"uv":[1.5625,12.375,3.0625,12.625],"tintindex":0,"rotation":0,"texture":"#0"},"north":{"uv":[1.5625,12.375,3.0625,12.625],"tintindex":0,"rotation":0,"texture":"#0"},"west":{"uv":[1.5625,12.625,1.8125,12.875],"tintindex":0,"rotation":0,"texture":"#0"},"up":{"uv":[1.8125,12.625,3.3125,12.875],"tintindex":0,"rotation":0,"texture":"#0"},"down":{"uv":[1.5625,12.875,3.0625,13.125],"tintindex":0,"rotation":0,"texture":"#0"}}},{"from":[6.0,11.5,2.0500002],"to":[18.0,14.0,10.05],"faces":{"south":{"uv":[1.5625,15.3125,3.0625,15.625],"tintindex":0,"rotation":0,"texture":"#0"},"north":{"uv":[1.5625,15.3125,3.0625,15.625],"tintindex":0,"rotation":0,"texture":"#0"},"up":{"uv":[1.5625,14.3125,3.0625,15.25],"tintindex":0,"rotation":0,"texture":"#0"}}},{"from":[18.1,7.5,0.0],"to":[18.1,14.0,24.0],"faces":{"east":{"uv":[3.0,10.1875,0.0,11.0],"tintindex":0,"rotation":0,"texture":"#0"},"west":{"uv":[0.0,10.1875,3.0,11.0],"tintindex":0,"rotation":0,"texture":"#0"}}},{"from":[6.0,11.5,2.0],"to":[18.0,17.0,2.0],"faces":{"south":{"uv":[0.0,12.5,1.5,13.1875],"tintindex":0,"rotation":0,"texture":"#0"},"north":{"uv":[0.0,12.5,1.5,13.1875],"tintindex":0,"rotation":0,"texture":"#0"}}},{"from":[5.9,7.5,0.0],"to":[5.9,14.0,24.0],"faces":{"east":{"uv":[3.0,10.1875,0.0,11.0],"tintindex":0,"rotation":0,"texture":"#0"},"west":{"uv":[0.0,10.1875,3.0,11.0],"tintindex":0,"rotation":0,"texture":"#0"}}},{"from":[18.05,10.0,0.0],"to":[18.05,20.5,24.0],"faces":{"east":{"uv":[3.0,11.0625,0.0,12.375],"tintindex":0,"rotation":0,"texture":"#0"},"west":{"uv":[0.0,11.0625,3.0,12.375],"tintindex":0,"rotation":0,"texture":"#0"}}},{"from":[6.0,18.0,20.5],"to":[18.0,20.0,22.5],"faces":{"east":{"uv":[1.8125,12.625,1.5625,12.875],"tintindex":0,"rotation":0,"texture":"#0"},"south":{"uv":[1.5625,12.375,3.0625,12.625],"tintindex":0,"rotation":0,"texture":"#0"},"north":{"uv":[1.5625,12.375,3.0625,12.625],"tintindex":0,"rotation":0,"texture":"#0"},"west":{"uv":[1.5625,12.625,1.8125,12.875],"tintindex":0,"rotation":0,"texture":"#0"},"up":{"uv":[1.8125,12.625,3.3125,12.875],"tintindex":0,"rotation":0,"texture":"#0"},"down":{"uv":[1.5625,12.875,3.0625,13.125],"tintindex":0,"rotation":0,"texture":"#0"}}},{"from":[6.0,11.5,21.0],"to":[18.0,18.0,21.0],"faces":{"south":{"uv":[0.0,12.375,1.5,13.1875],"tintindex":0,"rotation":0,"texture":"#0"},"north":{"uv":[0.0,12.375,1.5,13.1875],"tintindex":0,"rotation":0,"texture":"#0"}}},{"from":[6.0,11.5,2.0],"to":[18.0,11.5,21.0],"faces":{"up":{"uv":[0.0,13.25,1.5,15.625],"tintindex":0,"rotation":0,"texture":"#0"},"down":{"uv":[0.0,13.25,1.5,15.625],"tintindex":0,"rotation":0,"texture":"#0"}}},{"from":[5.95,10.0,0.0],"to":[5.95,20.5,24.0],"faces":{"east":{"uv":[3.0,11.0625,0.0,12.375],"tintindex":0,"rotation":0,"texture":"#0"},"west":{"uv":[0.0,11.0625,3.0,12.375],"tintindex":0,"rotation":0,"texture":"#0"}}}]}