{"textures":{"0":"modelengine:entity/bs_lny_ox_texture","1":"modelengine:entity/bs_lny_ox_texture2"},"elements":[{"from":[6.6857142,3.8285713,6.6857142],"to":[9.314285,8.742857,9.314285],"rotation":{"angle":0.0,"axis":"y","origin":[6.5714283,4.0,4.714286]},"faces":{"east":{"uv":[9.0,9.5,10.0,11.5],"rotation":0,"texture":"#1","tintindex":0},"south":{"uv":[0.0,10.0,1.0,12.0],"rotation":0,"texture":"#1","tintindex":0},"north":{"uv":[3.25,9.5,4.25,11.5],"rotation":0,"texture":"#1","tintindex":0},"west":{"uv":[1.0,10.0,2.0,12.0],"rotation":0,"texture":"#1","tintindex":0},"up":{"uv":[11.25,8.0,10.25,7.0],"rotation":0,"texture":"#1","tintindex":0},"down":{"uv":[11.25,8.0,10.25,9.0],"rotation":0,"texture":"#1","tintindex":0}}},{"from":[6.857143,4.0,6.857143],"to":[9.142858,8.571428,9.142858],"rotation":{"angle":0.0,"axis":"y","origin":[6.5714283,4.0,4.714286]},"faces":{"east":{"uv":[7.0,12.0,8.0,14.0],"rotation":0,"texture":"#0","tintindex":0},"south":{"uv":[12.25,5.5,13.25,7.5],"rotation":0,"texture":"#0","tintindex":0},"north":{"uv":[6.0,12.0,7.0,14.0],"rotation":0,"texture":"#0","tintindex":0},"west":{"uv":[12.75,7.5,13.75,9.5],"rotation":0,"texture":"#0","tintindex":0},"up":{"uv":[14.0,3.5,13.0,2.5],"rotation":0,"texture":"#0","tintindex":0},"down":{"uv":[14.0,3.5,13.0,4.5],"rotation":0,"texture":"#0","tintindex":0}}}],"display":{"head":{"translation":[0.0,-6.4,0.0],"scale":[4.0,4.0,4.0]}}}