{"textures":{"0":"modelengine:entity/bs_lny_ox_texture"},"elements":[{"from":[7.714286,7.829313,7.1784506],"to":[8.285714,7.829313,8.892736],"rotation":{"angle":-22.5,"axis":"x","origin":[8.0,8.400742,7.4641647]},"faces":{"east":{"uv":[0.0,0.0,0.75,0.0],"rotation":0,"texture":"#0","tintindex":0},"south":{"uv":[0.0,0.0,0.25,0.0],"rotation":0,"texture":"#0","tintindex":0},"north":{"uv":[0.0,0.0,0.25,0.0],"rotation":0,"texture":"#0","tintindex":0},"west":{"uv":[0.0,0.0,0.75,0.0],"rotation":0,"texture":"#0","tintindex":0},"up":{"uv":[3.0,6.25,2.75,5.5],"rotation":0,"texture":"#0","tintindex":0},"down":{"uv":[3.0,6.25,2.75,7.0],"rotation":0,"texture":"#0","tintindex":0}}},{"from":[6.857143,9.353272,8.971165],"to":[9.142858,9.353272,11.25688],"rotation":{"angle":-45.0,"axis":"x","origin":[8.857143,8.924701,10.114022]},"faces":{"east":{"uv":[0.0,0.0,1.0,0.0],"rotation":0,"texture":"#0","tintindex":0},"south":{"uv":[0.0,0.0,1.0,0.0],"rotation":0,"texture":"#0","tintindex":0},"north":{"uv":[0.0,0.0,1.0,0.0],"rotation":0,"texture":"#0","tintindex":0},"west":{"uv":[0.0,0.0,1.0,0.0],"rotation":0,"texture":"#0","tintindex":0},"up":{"uv":[12.75,14.5,11.75,13.5],"rotation":0,"texture":"#0","tintindex":0},"down":{"uv":[12.75,13.5,11.75,14.5],"rotation":0,"texture":"#0","tintindex":0}}}],"display":{"head":{"translation":[0.0,-6.4,0.0],"scale":[4.0,4.0,4.0]}}}